isocompy/__init__.py
isocompy/change_meteo_file_names.py
isocompy/create_maps.py
isocompy/cv_uncertainty.py
isocompy/data_prep.py
isocompy/data_preparation.py
isocompy/feature_select.py
isocompy/gen_traj_prediction.py
isocompy/isocompy_tool_funcs.py
isocompy/model_fitting.py
isocompy/pysplit_funcs_for_meteo_model.py
isocompy/reg_model.py
isocompy/requirements.txt
isocompy/tools.py
isocompy-1.0.2.dist-info/LICENSE
isocompy-1.0.2.dist-info/WHEEL
isocompy-1.0.2.dist-info/METADATA
isocompy-1.0.2.dist-info/RECORD
