Metadata-Version: 2.1
Name: isocompy
Version: 1.0.2
Summary: An open source library for environmental isotopic modelling 
Author-email: IDAEA-CSIC / Ashkan Hassanzadeh <ashkan.hassanzadeh@gmail.com>
Requires-Python: >=3.3
Classifier: License :: OSI Approved :: GNU Affero General Public License v3 or later (AGPLv3+)
Classifier: Programming Language :: Python :: 3
Classifier: Development Status :: 4 - Beta
Requires-Dist: pandas
Requires-Dist: pylr2
Requires-Dist: dill
Requires-Dist: geopandas
Requires-Dist: bokeh
Requires-Dist: statsmodels
Requires-Dist: numpy
Requires-Dist: tabulate
Requires-Dist: matplotlib
Requires-Dist: Shapely
Requires-Dist: scikit_learn
Project-URL: home-page, https://github.com/IDAEA-EVS/Isocompy
